VKPyKit/DT.py
VKPyKit/EDA.py
VKPyKit/LR.py
VKPyKit/MLM.py
VKPyKit/VKPy.py
VKPyKit/__init__.py
vkpykit-0.4.10.dist-info/licenses/LICENSE
vkpykit-0.4.10.dist-info/METADATA
vkpykit-0.4.10.dist-info/WHEEL
vkpykit-0.4.10.dist-info/top_level.txt
vkpykit-0.4.10.dist-info/RECORD
