Metadata-Version: 2.4
Name: VKPyKit
Version: 0.4.10
Summary: Packaged functions for Machine Learning and Data Science tasks.
Home-page: https://github.com/assignarc/VKPyKit
Author: Vishal Khapre
Maintainer: Vishal Khapre
License-Expression: MIT
Project-URL: Homepage, https://github.com/assignarc/VKPyKit
Project-URL: Bug Reports, https://github.com/assignarc/VKPyKit/issues
Project-URL: Funding, https://donate.pypi.org
Project-URL: Source, https://github.com/assignarc/VKPyKit
Keywords: Python,Machine Learning,data science,utilities
Classifier: Development Status :: 4 - Beta
Classifier: Intended Audience :: Developers
Classifier: Topic :: Software Development :: Build Tools
Classifier: Programming Language :: Python :: 3.9
Classifier: Programming Language :: Python :: 3.10
Classifier: Programming Language :: Python :: 3.11
Classifier: Programming Language :: Python :: 3.12
Requires-Python: >=3.9
License-File: LICENSE
Requires-Dist: numpy
Requires-Dist: pandas
Requires-Dist: scikit-learn
Requires-Dist: matplotlib
Requires-Dist: seaborn
Requires-Dist: openpyxl
Requires-Dist: plotly
Requires-Dist: tensorflow
Requires-Dist: keras
Provides-Extra: dev
Requires-Dist: check-manifest; extra == "dev"
Provides-Extra: test
Requires-Dist: pytest>=7.0; extra == "test"
Requires-Dist: pytest-cov>=4.0; extra == "test"
Requires-Dist: pytest-mock>=3.10; extra == "test"
Dynamic: home-page
Dynamic: license-file
